calitp_map_utils/__init__.py
calitp_map_utils/__main__.py
calitp_map_utils/cli.py
calitp_map_utils-2024.5.23.dist-info/METADATA
calitp_map_utils-2024.5.23.dist-info/WHEEL
calitp_map_utils-2024.5.23.dist-info/RECORD
