Metadata-Version: 2.1
Name: calitp_map_utils
Version: 2024.5.23
Summary: 
Author: Andrew Vaccaro
Author-email: andrew.v@jarv.us
Requires-Python: >=3.11,<3.12
Classifier: Programming Language :: Python :: 3
Classifier: Programming Language :: Python :: 3.11
Requires-Dist: furl (>=2.1.3,<3.0.0)
Requires-Dist: gcsfs (>=2023.6.0,<2024.0.0)
Requires-Dist: geojson-pydantic (>=0.6.1,<0.7.0)
Requires-Dist: pydantic (>=1.10.7,<2.0.0)
Requires-Dist: pyyaml (>=6.0,<7.0)
Requires-Dist: requests (>=2.24.0,<3.0.0)
Requires-Dist: tqdm (>=4.64.0,<5.0.0)
Requires-Dist: typer (>=0.9.0,<0.10.0)
